dolphin_memory_engine/__init__.py
dolphin_memory_engine/_dolphin_memory_engine.cp313-win_amd64.pyd
dolphin_memory_engine/dolphin-memory-engine.lib
dolphin_memory_engine_mpn-0.1.1.dist-info/LICENSE
dolphin_memory_engine_mpn-0.1.1.dist-info/METADATA
dolphin_memory_engine_mpn-0.1.1.dist-info/WHEEL
dolphin_memory_engine_mpn-0.1.1.dist-info/top_level.txt
dolphin_memory_engine_mpn-0.1.1.dist-info/RECORD
