Metadata-Version: 2.1
Name: dolphin-memory-engine-mpn
Version: 0.1.1
Summary: Fork of a software with support for MPN Dolphin.
Home-page: https://github.com/henriquegemignani/py-dolphin-memory-engine
Author: Henrique Gemignani
Author-email: naylahanegan@gmail.com
Project-URL: Homepage, https://github.com/henriquegemignani/py-dolphin-memory-engine
Classifier: License :: OSI Approved :: MIT License
Classifier: Development Status :: 3 - Alpha
Classifier: Intended Audience :: Developers
Classifier: Programming Language :: Python :: 3.8
Classifier: Programming Language :: Python :: 3.9
Classifier: Programming Language :: Python :: 3.10
Classifier: Programming Language :: Python :: 3.11
Classifier: Programming Language :: Python :: 3.12
Requires-Python: >=3.8
License-File: LICENSE
Provides-Extra: test
Requires-Dist: pytest; extra == "test"
Requires-Dist: pytest-cov; extra == "test"
